luca/__init__.py
luca/main.py
luca_cli-0.1.5.dist-info/METADATA
luca_cli-0.1.5.dist-info/WHEEL
luca_cli-0.1.5.dist-info/entry_points.txt
luca_cli-0.1.5.dist-info/top_level.txt
luca_cli-0.1.5.dist-info/RECORD
