Metadata-Version: 2.4
Name: luca-cli
Version: 0.1.5
Summary: CLI tool for the Luca assistant
Home-page: https://github.com/hgarud/client
Author: Hrishi Garud
Author-email: Hrishi Garud <hrishi.garud@gmail.com>
Project-URL: Homepage, https://github.com/hgarud/client
Classifier: Programming Language :: Python :: 3
Classifier: License :: OSI Approved :: MIT License
Classifier: Operating System :: OS Independent
Requires-Python: >=3.6
Requires-Dist: requests
Dynamic: author
Dynamic: home-page
Dynamic: requires-python
